p3dopenvr/__init__.py
p3dopenvr/definitions.py
p3dopenvr/hand.py
p3dopenvr/p3dopenvr.py
p3dopenvr/skeleton.py
p3dopenvr/version.py
panda3d_openvr-0.2.0.dist-info/LICENSE.txt
panda3d_openvr-0.2.0.dist-info/METADATA
panda3d_openvr-0.2.0.dist-info/WHEEL
panda3d_openvr-0.2.0.dist-info/top_level.txt
panda3d_openvr-0.2.0.dist-info/RECORD
