Metadata-Version: 2.1
Name: panda3d-openvr
Version: 0.2.0
Summary: OpenVR support for Panda3D
Home-page: https://github.com/el-dee/panda3d-openvr
Author: Laurent Deru
Author-email: laurent.deru@gmail.com
License: BSD
Keywords: panda3d openvr
Platform: UNKNOWN
Classifier: Development Status :: 4 - Beta
Classifier: License :: OSI Approved :: BSD License
Classifier: Programming Language :: Python
Classifier: Programming Language :: Python :: 3
Classifier: Programming Language :: Python :: 3.5
Classifier: Programming Language :: Python :: 3.6
Classifier: Programming Language :: Python :: 3.7
Classifier: Programming Language :: Python :: 3.8
Requires-Python: >=3.5
Requires-Dist: openvr
Requires-Dist: panda3d
